homemade_mcp/__init__.py
homemade_mcp/__main__.py
homemade_mcp/adapters/__init__.py
homemade_mcp/adapters/base.py
homemade_mcp/adapters/gemini_adapter.py
homemade_mcp/adapters/mistral_ocr_adapter.py
homemade_mcp/adapters/openai_adapter.py
homemade_mcp/adapters/utils.py
homemade_mcp/client.py
homemade_mcp/schemas.py
homemade_mcp-0.1.0.dist-info/LICENSE
homemade_mcp-0.1.0.dist-info/METADATA
homemade_mcp-0.1.0.dist-info/WHEEL
homemade_mcp-0.1.0.dist-info/entry_points.txt
homemade_mcp-0.1.0.dist-info/RECORD
