Metadata-Version: 2.3
Name: homemade-mcp
Version: 0.1.0
Summary: Homemade-MCP is a tiny Python library that gives you one standard input/output format for multiple AI providers.
License: MIT
Author: fllin1
Author-email: 1florentlin@gmail.com
Requires-Python: >=3.12
Classifier: License :: OSI Approved :: MIT License
Classifier: Programming Language :: Python :: 3
Classifier: Programming Language :: Python :: 3.12
Classifier: Programming Language :: Python :: 3.13
Requires-Dist: google-genai (>=1.31.0,<2.0.0)
Requires-Dist: httpx (>=0.28.1,<0.29.0)
Requires-Dist: openai (>=1.101.0,<2.0.0)
Requires-Dist: pillow (>=11.3.0,<12.0.0)
Requires-Dist: pydantic (>=2.11.7,<3.0.0)
Requires-Dist: pypdfium2 (>=4.30.0,<5.0.0)
Requires-Dist: typer (>=0.16.1,<0.17.0)
